notion_webhook/__init__.py
notion_webhook/db.py
notion_webhook/server/__init__.py
notion_webhook/server/handler.py
notion_webhook/server/http.py
secnex_notion_webhook_server-0.0.3.dist-info/licenses/LICENSE
secnex_notion_webhook_server-0.0.3.dist-info/METADATA
secnex_notion_webhook_server-0.0.3.dist-info/WHEEL
secnex_notion_webhook_server-0.0.3.dist-info/top_level.txt
secnex_notion_webhook_server-0.0.3.dist-info/RECORD
