Metadata-Version: 2.4
Name: secnex_notion_webhook_server
Version: 0.0.3
Summary: A package to create a webhook server that can be used to handle Notion webhooks and trigger actions
Author-email: Björn Benouarets <bjoern@secnex.io>
License-Expression: MIT
Project-URL: Homepage, https://github.com/secnex/notion-webhook-server
Project-URL: Issues, https://github.com/secnex/notion-webhook-server/issues
Classifier: Programming Language :: Python :: 3
Classifier: Operating System :: OS Independent
Requires-Python: >=3.9
License-File: LICENSE
Dynamic: license-file
